<?xml version="1.0" encoding="UTF-8"?>
<tour apprev="22555" appversion="8.0.2" hassounds="0" start="node2">
  <panorama id="node2">
    <input height="1680" levelbias="0.400" levelbiashidpi="1.000" levelingpitch="0" levelingroll="0" leveltilesize="1022" leveltileurl="tiles/node2/cf_%c/l_%l/c_%x/tile_%y.jpg" overlap="1" width="1680">
      <level height="1680" predecode="0" preload="0" width="1680"/>
      <level height="840" predecode="1" preload="1" width="840"/>
      <preview color="0x808080" strip="1"/>
    </input>
    <userdata altitude="176.30" author="" capturedatetime="2026-06-09T08:10:38Z" comment="" copyright="" customnodeid="" datetime="09.06.2026 8:10" description="" heading="195.1" hideinlist="0" info="" latitude="55.42317222" longitude="37.55280833" nodeid="node2" source="" tags="" title=""/>
    <view fovmode="2" pannorth="195.1">
      <start fov="93.2432" pan="100.376" projection="4" tilt="6.84896"/>
      <flyin fov="170" pan="0" projection="9" tilt="-90"/>
      <min fov="1" pan="0" tilt="-90"/>
      <max fov="120" fovfisheye="360" fovstereographic="270" pan="360" scaletofit="0" tilt="90"/>
    </view>
    <hotspots>
      <hotspot description="" distance="1.26571" id="Point01" pan="138.14" skinid="ht_node" target="" tilt="-0.21" title="" url="{node3}"/>
      <hotspot description="" distance="7.82819" id="Point02" pan="100.19" skinid="ht_node" target="" tilt="-0.24" title="" url="{node5}"/>
      <hotspot description="" id="Point04" pan="158.12" skinid="ht_url" target="_blank" tilt="4.45" title="" url="viewer.html?model=air_conditioner.glb"/>
    </hotspots>
    <media/>
    <animation animsequence="Animation01" clipsrandom="0" syncanimationwithvideo="0" useinautorotation="0"/>
  </panorama>
  <panorama id="node3">
    <input height="1680" levelbias="0.400" levelbiashidpi="1.000" levelingpitch="0" levelingroll="0" leveltilesize="1022" leveltileurl="tiles/node3/cf_%c/l_%l/c_%x/tile_%y.jpg" overlap="1" width="1680">
      <level height="1680" predecode="0" preload="0" width="1680"/>
      <level height="840" predecode="1" preload="1" width="840"/>
      <preview color="0x808080" strip="1"/>
    </input>
    <userdata altitude="176.20" author="" capturedatetime="2026-06-09T08:10:09Z" comment="" copyright="" customnodeid="" datetime="09.06.2026 8:10" description="" heading="67.9" hideinlist="0" info="" latitude="55.42316944" longitude="37.55282778" nodeid="node3" source="" tags="" title=""/>
    <view fovmode="2" pannorth="67.9">
      <start fov="118.027" pan="-178.217" projection="4" tilt="1.00344"/>
      <flyin fov="170" pan="0" projection="9" tilt="-90"/>
      <min fov="1" pan="0" tilt="-90"/>
      <max fov="120" fovfisheye="360" fovstereographic="270" pan="360" scaletofit="0" tilt="90"/>
    </view>
    <hotspots>
      <hotspot description="" distance="1.26571" id="Point01" pan="-89.78" skinid="ht_node" target="" tilt="3.54" title="" url="{node2}"/>
      <hotspot description="" distance="6.92672" id="Point02" pan="72.16" skinid="ht_node" target="" tilt="-3" title="" url="{node9}"/>
      <hotspot description="" distance="3.2632" id="Point03" pan="131.66" skinid="ht_node" target="" tilt="2.55" title="" url="{node4}"/>
      <hotspot description="" distance="6.67293" id="Point04" pan="-4.21" skinid="ht_node" target="" tilt="5.05" title="" url="{node5}"/>
    </hotspots>
    <media/>
    <animation animsequence="Animation01" clipsrandom="0" syncanimationwithvideo="0" useinautorotation="0"/>
  </panorama>
  <panorama id="node4">
    <input height="1680" levelbias="0.400" levelbiashidpi="1.000" levelingpitch="0" levelingroll="0" leveltilesize="1022" leveltileurl="tiles/node4/cf_%c/l_%l/c_%x/tile_%y.jpg" overlap="1" width="1680">
      <level height="1680" predecode="0" preload="0" width="1680"/>
      <level height="840" predecode="1" preload="1" width="840"/>
      <preview color="0x808080" strip="1"/>
    </input>
    <userdata altitude="177.70" author="" capturedatetime="2026-06-09T08:11:13Z" comment="" copyright="" customnodeid="" datetime="09.06.2026 8:11" description="" heading="183.3" hideinlist="0" info="" latitude="55.42319722" longitude="37.55281111" nodeid="node4" source="" tags="" title=""/>
    <view fovmode="2" pannorth="183.3">
      <start fov="127.674" pan="92.5465" projection="4" tilt="-10.1803"/>
      <flyin fov="170" pan="0" projection="9" tilt="-90"/>
      <min fov="1" pan="0" tilt="-90"/>
      <max fov="120" fovfisheye="360" fovstereographic="270" pan="360" scaletofit="0" tilt="90"/>
    </view>
    <hotspots>
      <hotspot description="" distance="3.2632" id="Point01" pan="78.77" skinid="ht_node" target="" tilt="0.76" title="" url="{node3}"/>
    </hotspots>
    <media/>
    <animation animsequence="Animation01" clipsrandom="0" syncanimationwithvideo="0" useinautorotation="0"/>
  </panorama>
  <panorama id="node5">
    <input height="1680" levelbias="0.400" levelbiashidpi="1.000" levelingpitch="0" levelingroll="0" leveltilesize="1022" leveltileurl="tiles/node5/cf_%c/l_%l/c_%x/tile_%y.jpg" overlap="1" width="1680">
      <level height="1680" predecode="0" preload="0" width="1680"/>
      <level height="840" predecode="1" preload="1" width="840"/>
      <preview color="0x808080" strip="1"/>
    </input>
    <userdata altitude="176.20" author="" capturedatetime="2026-06-09T08:12:00Z" comment="" copyright="" customnodeid="" datetime="09.06.2026 8:12" description="" heading="32.3" hideinlist="0" info="" latitude="55.42313056" longitude="37.55290833" nodeid="node5" source="" tags="" title=""/>
    <view fovmode="2" pannorth="32.3">
      <start fov="138.11" pan="-100.443" projection="4" tilt="3.41125"/>
      <flyin fov="170" pan="0" projection="9" tilt="-90"/>
      <min fov="1" pan="0" tilt="-90"/>
      <max fov="120" fovfisheye="360" fovstereographic="270" pan="360" scaletofit="0" tilt="90"/>
    </view>
    <hotspots>
      <hotspot description="" distance="6.67293" id="Point01" pan="105" skinid="ht_node" target="" tilt="-6.72" title="" url="{node3}"/>
      <hotspot description="" distance="7.82819" id="Point02" pan="119.16" skinid="ht_node" target="" tilt="-6.92" title="" url="{node2}"/>
      <hotspot description="" distance="9.2679" id="Point03" pan="-160.55" skinid="ht_node" target="" tilt="-4.57" title="" url="{node6}"/>
      <hotspot description="" distance="9.84349" id="Point04" pan="7.48" skinid="ht_node" target="" tilt="-0.75" title="" url="{node8}"/>
      <hotspot description="" distance="10.2141" id="Point05" pan="-63.9" skinid="ht_node" target="" tilt="-5.49" title="" url="{node10}"/>
      <hotspot description="" distance="2.08604" id="Point06" pan="67.81" skinid="ht_node" target="" tilt="-0.67" title="" url="{node9}"/>
      <hotspot description="" distance="9.62184" id="Point07" pan="93.37" skinid="ht_node" target="" tilt="0.06" title="" url="{node4}"/>
      <hotspot description="" id="Point08" pan="159.75" skinid="ht_url" target="_blank" tilt="2.03" title="" url="https://wheil.com/wacu/dry/"/>
    </hotspots>
    <media/>
    <animation animsequence="Animation01" clipsrandom="0" syncanimationwithvideo="0" useinautorotation="0"/>
  </panorama>
  <panorama id="node6">
    <input height="1680" levelbias="0.400" levelbiashidpi="1.000" levelingpitch="0" levelingroll="0" leveltilesize="1022" leveltileurl="tiles/node6/cf_%c/l_%l/c_%x/tile_%y.jpg" overlap="1" width="1680">
      <level height="1680" predecode="0" preload="0" width="1680"/>
      <level height="840" predecode="1" preload="1" width="840"/>
      <preview color="0x808080" strip="1"/>
    </input>
    <userdata altitude="176.10" author="" capturedatetime="2026-06-09T08:12:24Z" comment="" copyright="" customnodeid="" datetime="09.06.2026 8:12" description="" heading="83.1" hideinlist="0" info="" latitude="55.42305278" longitude="37.55296111" nodeid="node6" source="" tags="" title=""/>
    <view fovmode="2" pannorth="83.1">
      <start fov="138.11" pan="141.722" projection="4" tilt="-2.02287"/>
      <flyin fov="170" pan="0" projection="9" tilt="-90"/>
      <min fov="1" pan="0" tilt="-90"/>
      <max fov="120" fovfisheye="360" fovstereographic="270" pan="360" scaletofit="0" tilt="90"/>
    </view>
    <hotspots>
      <hotspot description="" distance="7.18391" id="Point01" pan="175.82" skinid="ht_node" target="" tilt="-9.49" title="" url="{node7}"/>
      <hotspot description="" distance="9.2679" id="Point02" pan="93.29" skinid="ht_node" target="" tilt="-4.35" title="" url="{node5}"/>
    </hotspots>
    <media/>
    <animation animsequence="Animation01" clipsrandom="0" syncanimationwithvideo="0" useinautorotation="0"/>
  </panorama>
  <panorama id="node7">
    <input height="1680" levelbias="0.400" levelbiashidpi="1.000" levelingpitch="0" levelingroll="0" leveltilesize="1022" leveltileurl="tiles/node7/cf_%c/l_%l/c_%x/tile_%y.jpg" overlap="1" width="1680">
      <level height="1680" predecode="0" preload="0" width="1680"/>
      <level height="840" predecode="1" preload="1" width="840"/>
      <preview color="0x808080" strip="1"/>
    </input>
    <userdata altitude="176.10" author="" capturedatetime="2026-06-09T08:12:56Z" comment="" copyright="" customnodeid="" datetime="09.06.2026 8:12" description="" heading="197.9" hideinlist="0" info="" latitude="55.42302500" longitude="37.55285833" nodeid="node7" source="" tags="" title=""/>
    <view fovmode="2" pannorth="197.9">
      <start fov="127.674" pan="129.847" projection="4" tilt="0.64732"/>
      <flyin fov="170" pan="0" projection="9" tilt="-90"/>
      <min fov="1" pan="0" tilt="-90"/>
      <max fov="120" fovfisheye="360" fovstereographic="270" pan="360" scaletofit="0" tilt="90"/>
    </view>
    <hotspots>
      <hotspot description="" distance="7.18391" id="Point01" pan="74.97" skinid="ht_node" target="" tilt="-9.63" title="" url="{node6}"/>
    </hotspots>
    <media/>
    <animation animsequence="Animation01" clipsrandom="0" syncanimationwithvideo="0" useinautorotation="0"/>
  </panorama>
  <panorama id="node8">
    <input height="1680" levelbias="0.400" levelbiashidpi="1.000" levelingpitch="0" levelingroll="0" leveltilesize="1022" leveltileurl="tiles/node8/cf_%c/l_%l/c_%x/tile_%y.jpg" overlap="1" width="1680">
      <level height="1680" predecode="0" preload="0" width="1680"/>
      <level height="840" predecode="1" preload="1" width="840"/>
      <preview color="0x808080" strip="1"/>
    </input>
    <userdata altitude="176.20" author="" capturedatetime="2026-06-09T08:13:40Z" comment="" copyright="" customnodeid="" datetime="09.06.2026 8:13" description="" heading="320.2" hideinlist="0" info="" latitude="55.42304444" longitude="37.55294444" nodeid="node8" source="" tags="" title=""/>
    <view fovmode="2" pannorth="320.2">
      <start fov="118.027" pan="88.799" projection="4" tilt="1.02615"/>
      <flyin fov="170" pan="0" projection="9" tilt="-90"/>
      <min fov="1" pan="0" tilt="-90"/>
      <max fov="120" fovfisheye="360" fovstereographic="270" pan="360" scaletofit="0" tilt="90"/>
    </view>
    <hotspots>
      <hotspot description="" distance="8.83491" id="Point02" pan="-3.71" skinid="ht_node" target="" tilt="-0.14" title="" url="{node9}"/>
      <hotspot description="" distance="9.84349" id="Point03" pan="79.31" skinid="ht_node" target="" tilt="-9.04" title="" url="{node5}"/>
    </hotspots>
    <media/>
    <animation animsequence="Animation01" clipsrandom="0" syncanimationwithvideo="0" useinautorotation="0"/>
  </panorama>
  <panorama id="node9">
    <input height="1680" levelbias="0.400" levelbiashidpi="1.000" levelingpitch="0" levelingroll="0" leveltilesize="1022" leveltileurl="tiles/node9/cf_%c/l_%l/c_%x/tile_%y.jpg" overlap="1" width="1680">
      <level height="1680" predecode="0" preload="0" width="1680"/>
      <level height="840" predecode="1" preload="1" width="840"/>
      <preview color="0x808080" strip="1"/>
    </input>
    <userdata altitude="176.20" author="" capturedatetime="2026-06-09T08:14:12Z" comment="" copyright="" customnodeid="" datetime="09.06.2026 8:14" description="" heading="300.7" hideinlist="0" info="" latitude="55.42311667" longitude="37.55288611" nodeid="node9" source="" tags="" title=""/>
    <view fovmode="2" pannorth="300.7">
      <start fov="118.027" pan="83.3443" projection="4" tilt="-0.699792"/>
      <flyin fov="170" pan="0" projection="9" tilt="-90"/>
      <min fov="1" pan="0" tilt="-90"/>
      <max fov="120" fovfisheye="360" fovstereographic="270" pan="360" scaletofit="0" tilt="90"/>
    </view>
    <hotspots>
      <hotspot description="" distance="2.08604" id="Point01" pan="-101.535" skinid="ht_node" target="$fwd" tilt="0" title="" url="{node5}"/>
      <hotspot description="" distance="2.08604" id="Point02" pan="104.68" skinid="ht_node" target="" tilt="-5.69" title="" url="{node5}"/>
      <hotspot description="" distance="10.1303" id="Point03" pan="42.35" skinid="ht_node" target="" tilt="-0.12" title="" url="{node4}"/>
      <hotspot description="" distance="6.92672" id="Point04" pan="58.98" skinid="ht_node" target="" tilt="0.34" title="" url="{node3}"/>
    </hotspots>
    <media/>
    <animation animsequence="Animation01" clipsrandom="0" syncanimationwithvideo="0" useinautorotation="0"/>
  </panorama>
  <panorama id="node10">
    <input height="1680" levelbias="0.400" levelbiashidpi="1.000" levelingpitch="0" levelingroll="0" leveltilesize="1022" leveltileurl="tiles/node10/cf_%c/l_%l/c_%x/tile_%y.jpg" overlap="1" width="1680">
      <level height="1680" predecode="0" preload="0" width="1680"/>
      <level height="840" predecode="1" preload="1" width="840"/>
      <preview color="0x808080" strip="1"/>
    </input>
    <userdata altitude="175.90" author="" capturedatetime="2026-06-09T08:14:51Z" comment="" copyright="" customnodeid="" datetime="09.06.2026 8:14" description="" heading="70.6" hideinlist="0" info="" latitude="55.42305278" longitude="37.55299444" nodeid="node10" source="" tags="" title=""/>
    <view fovmode="2" pannorth="70.6">
      <start fov="118.027" pan="-4.58804" projection="4" tilt="0.986815"/>
      <flyin fov="170" pan="0" projection="9" tilt="-90"/>
      <min fov="1" pan="0" tilt="-90"/>
      <max fov="120" fovfisheye="360" fovstereographic="270" pan="360" scaletofit="0" tilt="90"/>
    </view>
    <hotspots>
      <hotspot description="" distance="10.2141" id="Point01" pan="164.73" skinid="ht_node" target="" tilt="-6.29" title="" url="{node5}"/>
      <hotspot description="" distance="3.28869" id="Point02" pan="152.08" skinid="ht_node" target="" tilt="-6.11" title="" url="{node8}"/>
      <hotspot description="" distance="14.7398" id="Point03" pan="18.04" skinid="ht_node" target="" tilt="4.35" title="" url="{node11}"/>
      <hotspot description="" distance="22.2244" id="Point04" pan="61.05" skinid="ht_node" target="" tilt="-10.36" title="" url="{node12}"/>
      <hotspot description="" distance="21.6807" id="Point05" pan="-12.86" skinid="ht_node" target="" tilt="-3.88" title="" url="{node15}"/>
    </hotspots>
    <media/>
    <animation animsequence="Animation01" clipsrandom="0" syncanimationwithvideo="0" useinautorotation="0"/>
  </panorama>
  <panorama id="node11">
    <input height="1680" levelbias="0.400" levelbiashidpi="1.000" levelingpitch="0" levelingroll="0" leveltilesize="1022" leveltileurl="tiles/node11/cf_%c/l_%l/c_%x/tile_%y.jpg" overlap="1" width="1680">
      <level height="1680" predecode="0" preload="0" width="1680"/>
      <level height="840" predecode="1" preload="1" width="840"/>
      <preview color="0x808080" strip="1"/>
    </input>
    <userdata altitude="175.90" author="" capturedatetime="2026-06-09T08:16:48Z" comment="" copyright="" customnodeid="" datetime="09.06.2026 8:16" description="" heading="114.4" hideinlist="0" info="" latitude="55.42295833" longitude="37.55315833" nodeid="node11" source="" tags="" title=""/>
    <view fovmode="2" pannorth="114.4">
      <start fov="118.027" pan="-145.316" projection="4" tilt="0.284481"/>
      <flyin fov="170" pan="0" projection="9" tilt="-90"/>
      <min fov="1" pan="0" tilt="-90"/>
      <max fov="120" fovfisheye="360" fovstereographic="270" pan="360" scaletofit="0" tilt="90"/>
    </view>
    <hotspots>
      <hotspot description="" distance="14.7398" id="Point01" pan="-123.17" skinid="ht_node" target="" tilt="-17.54" title="" url="{node10}"/>
    </hotspots>
    <media/>
    <animation animsequence="Animation01" clipsrandom="0" syncanimationwithvideo="0" useinautorotation="0"/>
  </panorama>
  <panorama id="node12">
    <input height="1680" levelbias="0.400" levelbiashidpi="1.000" levelingpitch="0" levelingroll="0" leveltilesize="1022" leveltileurl="tiles/node12/cf_%c/l_%l/c_%x/tile_%y.jpg" overlap="1" width="1680">
      <level height="1680" predecode="0" preload="0" width="1680"/>
      <level height="840" predecode="1" preload="1" width="840"/>
      <preview color="0x808080" strip="1"/>
    </input>
    <userdata altitude="175.90" author="" capturedatetime="2026-06-09T08:17:44Z" comment="" copyright="" customnodeid="" datetime="09.06.2026 8:17" description="" heading="353.1" hideinlist="0" info="" latitude="55.42303056" longitude="37.55334444" nodeid="node12" source="" tags="" title=""/>
    <view fovmode="2" pannorth="353.1">
      <start fov="118.027" pan="121.79" projection="4" tilt="-6.73808"/>
      <flyin fov="170" pan="0" projection="9" tilt="-90"/>
      <min fov="1" pan="0" tilt="-90"/>
      <max fov="120" fovfisheye="360" fovstereographic="270" pan="360" scaletofit="0" tilt="90"/>
    </view>
    <hotspots>
      <hotspot description="" distance="22.2244" id="Point01" pan="114.42" skinid="ht_node" target="" tilt="-6.95" title="" url="{node10}"/>
      <hotspot description="" distance="2.62351" id="Point02" pan="-149.49" skinid="ht_node" target="" tilt="-15.71" title="" url="{node13}"/>
    </hotspots>
    <media/>
    <animation animsequence="Animation01" clipsrandom="0" syncanimationwithvideo="0" useinautorotation="0"/>
  </panorama>
  <panorama id="node13">
    <input height="1680" levelbias="0.400" levelbiashidpi="1.000" levelingpitch="0" levelingroll="0" leveltilesize="1022" leveltileurl="tiles/node13/cf_%c/l_%l/c_%x/tile_%y.jpg" overlap="1" width="1680">
      <level height="1680" predecode="0" preload="0" width="1680"/>
      <level height="840" predecode="1" preload="1" width="840"/>
      <preview color="0x808080" strip="1"/>
    </input>
    <userdata altitude="175.90" author="" capturedatetime="2026-06-09T08:18:06Z" comment="" copyright="" customnodeid="" datetime="09.06.2026 8:18" description="" heading="265.5" hideinlist="0" info="" latitude="55.42302222" longitude="37.55338333" nodeid="node13" source="" tags="" title=""/>
    <view fovmode="2" pannorth="265.5">
      <start fov="118.027" pan="-51.567" projection="4" tilt="-0.291186"/>
      <flyin fov="170" pan="0" projection="9" tilt="-90"/>
      <min fov="1" pan="0" tilt="-90"/>
      <max fov="120" fovfisheye="360" fovstereographic="270" pan="360" scaletofit="0" tilt="90"/>
    </view>
    <hotspots>
      <hotspot description="" distance="2.62351" id="Point01" pan="-65.54" skinid="ht_node" target="" tilt="3.04" title="" url="{node12}"/>
    </hotspots>
    <media/>
    <animation animsequence="Animation01" clipsrandom="0" syncanimationwithvideo="0" useinautorotation="0"/>
  </panorama>
  <panorama id="node15">
    <input height="1680" levelbias="0.400" levelbiashidpi="1.000" levelingpitch="0" levelingroll="0" leveltilesize="1022" leveltileurl="tiles/node15/cf_%c/l_%l/c_%x/tile_%y.jpg" overlap="1" width="1680">
      <level height="1680" predecode="0" preload="0" width="1680"/>
      <level height="840" predecode="1" preload="1" width="840"/>
      <preview color="0x808080" strip="1"/>
    </input>
    <userdata altitude="175.90" author="" capturedatetime="2026-06-09T08:19:21Z" comment="" copyright="" customnodeid="" datetime="09.06.2026 8:19" description="" heading="196.5" hideinlist="0" info="" latitude="55.42300556" longitude="37.55332778" nodeid="node15" source="" tags="" title=""/>
    <view fovmode="2" pannorth="196.5">
      <start fov="109.109" pan="175.312" projection="4" tilt="-9.20958"/>
      <flyin fov="170" pan="0" projection="9" tilt="-90"/>
      <min fov="1" pan="0" tilt="-90"/>
      <max fov="120" fovfisheye="360" fovstereographic="270" pan="360" scaletofit="0" tilt="90"/>
    </view>
    <hotspots>
      <hotspot description="" distance="11.9131" id="Point01" pan="-104.71" skinid="ht_node" target="" tilt="1.39" title="" url="{node11}"/>
      <hotspot description="" distance="21.6807" id="Point02" pan="-96.79" skinid="ht_node" target="" tilt="-2.89" title="" url="{node10}"/>
      <hotspot description="" distance="14.935" id="Point03" pan="-5.52" skinid="ht_node" target="" tilt="-2.82" title="" url="{node17}"/>
      <hotspot description="" distance="4.33858" id="Point04" pan="175.41" skinid="ht_node" target="" tilt="-4.47" title="" url="{node18}"/>
      <hotspot description="" distance="3.19634" id="Point05" pan="-124.51" skinid="ht_node" target="" tilt="-7.14" title="" url="{node19}"/>
      <hotspot description="" id="Point06" pan="-165.77" skinid="ht_image" target="" tilt="2.03" title="" url="images/page_cover-dry.webp"/>
    </hotspots>
    <media>
      <image clickmode="0" fov="44.431" handcursor="0" height="1080" hidepinned="0" id="Element01" pan="80.279" popbackmode="0" popoutscaling="100" rotx="-21.183" roty="-10.464" rotz="-2.578" stretch="1.291" tilt="-14.267" width="1920">
        <source height="1080" url="media/page_cover-dry.webp" width="1920"/>
        <source height="540" url="media/page_cover-dry__s1.webp" width="960"/>
      </image>
    </media>
    <animation animsequence="Animation01" clipsrandom="0" syncanimationwithvideo="0" useinautorotation="0"/>
  </panorama>
  <panorama id="node17">
    <input height="1680" levelbias="0.400" levelbiashidpi="1.000" levelingpitch="0" levelingroll="0" leveltilesize="1022" leveltileurl="tiles/node17/cf_%c/l_%l/c_%x/tile_%y.jpg" overlap="1" width="1680">
      <level height="1680" predecode="0" preload="0" width="1680"/>
      <level height="840" predecode="1" preload="1" width="840"/>
      <preview color="0x808080" strip="1"/>
    </input>
    <userdata altitude="175.90" author="" capturedatetime="2026-06-09T08:20:25Z" comment="" copyright="" customnodeid="" datetime="09.06.2026 8:20" description="" heading="90.2" hideinlist="0" info="" latitude="55.42287500" longitude="37.55327222" nodeid="node17" source="" tags="" title=""/>
    <view fovmode="2" pannorth="90.2">
      <start fov="109.109" pan="126.5" projection="4" tilt="2.03223"/>
      <flyin fov="170" pan="0" projection="9" tilt="-90"/>
      <min fov="1" pan="0" tilt="-90"/>
      <max fov="120" fovfisheye="360" fovstereographic="270" pan="360" scaletofit="0" tilt="90"/>
    </view>
    <hotspots>
      <hotspot description="" distance="14.935" id="Point01" pan="88.55" skinid="ht_node" target="" tilt="-3.98" title="" url="{node15}"/>
    </hotspots>
    <media/>
    <animation animsequence="Animation01" clipsrandom="0" syncanimationwithvideo="0" useinautorotation="0"/>
  </panorama>
  <panorama id="node18">
    <input height="1680" levelbias="0.400" levelbiashidpi="1.000" levelingpitch="0" levelingroll="0" leveltilesize="1022" leveltileurl="tiles/node18/cf_%c/l_%l/c_%x/tile_%y.jpg" overlap="1" width="1680">
      <level height="1680" predecode="0" preload="0" width="1680"/>
      <level height="840" predecode="1" preload="1" width="840"/>
      <preview color="0x808080" strip="1"/>
    </input>
    <userdata altitude="175.90" author="" capturedatetime="2026-06-09T08:21:00Z" comment="" copyright="" customnodeid="" datetime="09.06.2026 8:21" description="" heading="94.8" hideinlist="0" info="" latitude="55.42296667" longitude="37.55332222" nodeid="node18" source="" tags="" title=""/>
    <view fovmode="2" pannorth="94.8">
      <start fov="109.109" pan="89.0297" projection="4" tilt="1.36564"/>
      <flyin fov="170" pan="0" projection="9" tilt="-90"/>
      <min fov="1" pan="0" tilt="-90"/>
      <max fov="120" fovfisheye="360" fovstereographic="270" pan="360" scaletofit="0" tilt="90"/>
    </view>
    <hotspots>
      <hotspot description="" distance="4.33858" id="Point01" pan="-90.85" skinid="ht_node" target="" tilt="-19.2" title="" url="{node15}"/>
      <hotspot description="" distance="10.6704" id="Point02" pan="-90.6" skinid="ht_node" target="" tilt="-1.99" title="" url="{node17}"/>
      <hotspot description="" distance="12.3991" id="Point03" pan="83.59" skinid="ht_node" target="" tilt="-5.22" title="" url="{node22}"/>
      <hotspot description="" distance="2.47073" id="Point04" pan="157.12" skinid="ht_node" target="" tilt="0.82" title="" url="{node19}"/>
    </hotspots>
    <media/>
    <animation animsequence="Animation01" clipsrandom="0" syncanimationwithvideo="0" useinautorotation="0"/>
  </panorama>
  <panorama id="node19">
    <input height="1680" levelbias="0.400" levelbiashidpi="1.000" levelingpitch="0" levelingroll="0" leveltilesize="1022" leveltileurl="tiles/node19/cf_%c/l_%l/c_%x/tile_%y.jpg" overlap="1" width="1680">
      <level height="1680" predecode="0" preload="0" width="1680"/>
      <level height="840" predecode="1" preload="1" width="840"/>
      <preview color="0x808080" strip="1"/>
    </input>
    <userdata altitude="175.90" author="" capturedatetime="2026-06-09T08:21:28Z" comment="" copyright="" customnodeid="" datetime="09.06.2026 8:21" description="" heading="113" hideinlist="0" info="" latitude="55.42298056" longitude="37.55335278" nodeid="node19" source="" tags="" title=""/>
    <view fovmode="2" pannorth="113">
      <start fov="127.674" pan="83.2654" projection="4" tilt="-4.36669"/>
      <flyin fov="170" pan="0" projection="9" tilt="-90"/>
      <min fov="1" pan="0" tilt="-90"/>
      <max fov="120" fovfisheye="360" fovstereographic="270" pan="360" scaletofit="0" tilt="90"/>
    </view>
    <hotspots>
      <hotspot description="" distance="8.19937" id="Point01" pan="97.51" skinid="ht_node" target="" tilt="0.0800001" title="" url="{node21}"/>
    </hotspots>
    <media/>
    <animation animsequence="Animation01" clipsrandom="0" syncanimationwithvideo="0" useinautorotation="0"/>
  </panorama>
  <panorama id="node21">
    <input height="1680" levelbias="0.400" levelbiashidpi="1.000" levelingpitch="0" levelingroll="0" leveltilesize="1022" leveltileurl="tiles/node21/cf_%c/l_%l/c_%x/tile_%y.jpg" overlap="1" width="1680">
      <level height="1680" predecode="0" preload="0" width="1680"/>
      <level height="840" predecode="1" preload="1" width="840"/>
      <preview color="0x808080" strip="1"/>
    </input>
    <userdata altitude="175.90" author="" capturedatetime="2026-06-09T08:22:24Z" comment="" copyright="" customnodeid="" datetime="09.06.2026 8:22" description="" heading="14.8" hideinlist="0" info="" latitude="55.42304722" longitude="37.55340833" nodeid="node21" source="" tags="" title=""/>
    <view fovmode="2" pannorth="14.8">
      <start fov="127.674" pan="-53.9429" projection="4" tilt="4.46383"/>
      <flyin fov="170" pan="0" projection="9" tilt="-90"/>
      <min fov="1" pan="0" tilt="-90"/>
      <max fov="120" fovfisheye="360" fovstereographic="270" pan="360" scaletofit="0" tilt="90"/>
    </view>
    <hotspots>
      <hotspot description="" distance="2.82198" id="Point01" pan="-89.13" skinid="ht_node" target="" tilt="-6.38" title="" url="{node22}"/>
    </hotspots>
    <media/>
    <animation animsequence="Animation01" clipsrandom="0" syncanimationwithvideo="0" useinautorotation="0"/>
  </panorama>
  <panorama id="node22">
    <input height="1680" levelbias="0.400" levelbiashidpi="1.000" levelingpitch="0" levelingroll="0" leveltilesize="1022" leveltileurl="tiles/node22/cf_%c/l_%l/c_%x/tile_%y.jpg" overlap="1" width="1680">
      <level height="1680" predecode="0" preload="0" width="1680"/>
      <level height="840" predecode="1" preload="1" width="840"/>
      <preview color="0x808080" strip="1"/>
    </input>
    <userdata altitude="175.90" author="" capturedatetime="2026-06-09T08:23:02Z" comment="" copyright="" customnodeid="" datetime="09.06.2026 8:23" description="" heading="156.1" hideinlist="0" info="" latitude="55.42305000" longitude="37.55345278" nodeid="node22" source="" tags="" title=""/>
    <view fovmode="2" pannorth="156.1">
      <start fov="118.027" pan="-177.056" projection="4" tilt="-5.47781"/>
      <flyin fov="170" pan="0" projection="9" tilt="-90"/>
      <min fov="1" pan="0" tilt="-90"/>
      <max fov="120" fovfisheye="360" fovstereographic="270" pan="360" scaletofit="0" tilt="90"/>
    </view>
    <hotspots>
      <hotspot description="" distance="2.82198" id="Point01" pan="-131.65" skinid="ht_node" target="" tilt="-1.83" title="" url="{node21}"/>
      <hotspot description="" distance="12.3991" id="Point02" pan="-65.08" skinid="ht_node" target="" tilt="-1.99" title="" url="{node18}"/>
    </hotspots>
    <media/>
    <animation animsequence="Animation01" clipsrandom="0" syncanimationwithvideo="0" useinautorotation="0"/>
  </panorama>
  <masternode>
    <userdata author="" comment="" copyright="" description="" tags="" title="" uuid="{c31a0bcb-b6af-4959-99c7-60e5b423f42e}"/>
    <transition blendcolor="0x000000" blendtime="1" delay="none" enabled="1" softedge="0" type="crossdissolve" zoomafterinfov="140" zoomafteroutfov="40" zoomfov="40" zoomin="0" zoomout="0" zoomoutpause="1" zoomspeed="2"/>
    <control contextfullscreen="1" contextprojections="0" contextvr="1" dblclickfullscreen="0" hideabout="0" invertcontrol="1" invertwheel="0" lockedkeyboard="0" lockedkeyboardzoom="0" lockedmouse="0" lockedwheel="0" rubberband="0" sensitivity="8" simulatemass="1" speedwheel="1" zoomcentercursor="1"/>
    <animationsequences>
      <sequence title="Animation01"/>
    </animationsequences>
    <hotspots smoothmovement="0">
      <label background="1" backgroundalpha="1" backgroundcolor="0xffffff" border="1" borderalpha="1" bordercolor="0x000000" borderradius="1" enabled="1" height="20" textalpha="1" textcolor="0x000000" width="180" wordwrap="1"/>
      <polystyle backgroundalpha="0.25098" backgroundcolor="0x0000ff" borderalpha="1" bordercolor="0x0000ff" handcursor="1" mode="0"/>
    </hotspots>
  </masternode>
</tour>
